algcol/__init__.py
algcol/max.py
algcol/test.py
code/__init__.py
code/test.py
testalg/__init__.py
testalg/test.py
algcol-0.0.4.dist-info/METADATA
algcol-0.0.4.dist-info/WHEEL
algcol-0.0.4.dist-info/top_level.txt
algcol-0.0.4.dist-info/RECORD
