Metadata-Version: 2.1
Name: algcol
Version: 0.0.4
Summary: A library of common algorithms
Home-page: https://github.com/remyd95/Algcol
Author: Remy Duijsens
Author-email: remyduijsens@gmail.com
Classifier: Programming Language :: Python :: 3
Classifier: License :: OSI Approved :: MIT License
Classifier: Operating System :: OS Independent
